LICENSE
README.md
setup.py
ai_openchat/__init__.py
ai_openchat/aiiohttp.py
ai_openchat/base_openai.py
ai_openchat/image_model.py
ai_openchat/model.py
ai_openchat/openai.py
ai_openchat/session.py
ai_openchat/token.py
ai_openchat.egg-info/PKG-INFO
ai_openchat.egg-info/SOURCES.txt
ai_openchat.egg-info/dependency_links.txt
ai_openchat.egg-info/requires.txt
ai_openchat.egg-info/top_level.txt