Metadata-Version: 2.1
Name: ai-openchat
Version: 1.1.8
Summary: Python module for asynchronous interaction with OpenAI 
Home-page: https://github.com/Whitev2/async-openai
Author: Whitev2
Author-email: maksfundd@gmail.com
License: MIT License, see LICENSE file
Download-URL: https://github.com/Whitev2/async-openai/archive/refs/tags/v.1.1.8.zip
Platform: UNKNOWN
Classifier: Operating System :: OS Independent
Classifier: Intended Audience :: End Users/Desktop
Classifier: Intended Audience :: Developers
Classifier: Programming Language :: Python :: 3.8
Classifier: Programming Language :: Python :: 3.10
Classifier: Programming Language :: Python :: 3.11
Classifier: Programming Language :: Python :: Implementation :: PyPy
Classifier: Programming Language :: Python :: Implementation :: CPython
License-File: LICENSE
